guidance/__init__.py
guidance/_grammar.py
guidance/_parser.py
guidance/_utils.py
guidance/_variable_stack.py
guidance/endpoints/__init__.py
guidance/endpoints/_deep_speed.py
guidance/endpoints/_llm.py
guidance/endpoints/_mock.py
guidance/endpoints/_openai.py
guidance/endpoints/_transformers.py
guidance/endpoints/caches/__init__.py
guidance/endpoints/caches/_cache.py
guidance/endpoints/caches/_diskcache.py
guidance/endpoints/caches/_gptcache.py
guidance/endpoints/transformers/__init__.py
guidance/endpoints/transformers/_koala.py
guidance/endpoints/transformers/_llama.py
guidance/endpoints/transformers/_mpt.py
guidance/endpoints/transformers/_stablelm.py
guidance/endpoints/transformers/_vicuna.py
guidance/library/__init__.py
guidance/library/_any_char.py
guidance/library/_any_char_but.py
guidance/library/_block.py
guidance/library/_char_range.py
guidance/library/_char_set.py
guidance/library/_gen.py
guidance/library/_one_or_more.py
guidance/library/_optional.py
guidance/library/_prefix_tree.py
guidance/library/_regex.py
guidance/library/_role.py
guidance/library/_silent.py
guidance/library/_substring.py
guidance/library/_tool.py
guidance/library/_zero_or_more.py
guidance/models/__init__.py
guidance/models/_llama_cpp.py
guidance/models/_local.py
guidance/models/_local_mock.py
guidance/models/_model.py
guidance/models/_openai.py
guidance/models/_transformers.py
guidance/models/_vertexai.py
guidance/models/transformers/__init__.py
guidance/models/transformers/_llama.py
guidance/models/vertexai/_PaLM2.py
guidance/models/vertexai/__init__.py
guidance/resources/main.js
guidance/selectors.py
agent_utils-0.1.0.dist-info/LICENSE
agent_utils-0.1.0.dist-info/METADATA
agent_utils-0.1.0.dist-info/WHEEL
agent_utils-0.1.0.dist-info/RECORD
