Metadata-Version: 2.1
Name: agent-utils
Version: 0.1.0
Summary: 
Author: anubrag
Author-email: b.anurag@aol.com
Requires-Python: >=3.8,<4.0
Classifier: Programming Language :: Python :: 3
Classifier: Programming Language :: Python :: 3.8
Classifier: Programming Language :: Python :: 3.9
Classifier: Programming Language :: Python :: 3.10
Classifier: Programming Language :: Python :: 3.11
Classifier: Programming Language :: Python :: 3.12
Provides-Extra: numpy
Provides-Extra: torch
Provides-Extra: transformers
Requires-Dist: aiohttp (>=3.8.1,<4.0.0)
Requires-Dist: diskcache (>=5.2.1,<6.0.0)
Requires-Dist: msal (>=1.16.0,<2.0.0)
Requires-Dist: nest_asyncio (>=1.5.3,<2.0.0)
Requires-Dist: openai (>=0.27.8,<0.28.0)
Requires-Dist: ordered_set (>=4.0.2,<5.0.0)
Requires-Dist: platformdirs (>=2.4.0,<3.0.0)
Requires-Dist: pyformlang (>=0.1.23,<0.2.0)
Requires-Dist: pygtrie (>=2.4.0,<3.0.0)
Requires-Dist: pyparsing (>=3.0.0,<4.0.0)
Requires-Dist: requests (>=2.26.0,<3.0.0)
Requires-Dist: tiktoken (>=0.3.0,<0.4.0)
